csi/__init__.py
csi/configuration.py
csi/experiment.py
csi/safety.py
csi/situation/__init__.py
csi/situation/components.py
csi/situation/coverage.py
csi/situation/domain.py
csi/situation/helpers.py
csi/situation/monitoring.py
csi/transform.py
csi/twin/__init__.py
csi/twin/importer.py
csi/twin/orm.py
py_csi_cobotics-0.2.1.dist-info/LICENSE.md
py_csi_cobotics-0.2.1.dist-info/WHEEL
py_csi_cobotics-0.2.1.dist-info/METADATA
py_csi_cobotics-0.2.1.dist-info/RECORD
