Metadata-Version: 2.1
Name: py-csi-cobotics
Version: 0.2.1
Summary: A Python framework for controlling and processing experiments built upon the CSI:Cobot Digital Twin
Home-page: https://github.com/Gaudeval/py-csi-cobotics
License: BSD-3-Clause
Author: Gaudeval
Author-email: bl778@york.ac.uk
Requires-Python: >=3.9,<4.0
Classifier: License :: OSI Approved :: BSD License
Classifier: Programming Language :: Python :: 3
Classifier: Programming Language :: Python :: 3.9
Requires-Dist: dataset (>=1.5.0,<2.0.0)
Requires-Dist: docker (>=5.0.3,<6.0.0)
Requires-Dist: drs (>=2.0.0,<3.0.0)
Requires-Dist: geneticalgorithm (>=1.0.2,<2.0.0)
Requires-Dist: jsonpath2 (>=0.4.4,<0.5.0)
Requires-Dist: metric-temporal-fuzzy-logic (>=0.0.6,<0.0.7)
Requires-Dist: qdpy (>=0.1.2,<0.2.0)
Requires-Dist: seaborn (>=0.11.2,<0.12.0)
Requires-Dist: tqdm (>=4.62.3,<5.0.0)
Requires-Dist: traces (>=0.6.0,<0.7.0)
Project-URL: Repository, https://github.com/Gaudeval/py-csi-cobotics
